tc/__init__.py
tc/py.typed
tc/alloy/__init__.py
tc/alloy/known_alloy.py
tc/alloy/types.py
tc/alloy/cli/__init__.py
tc/alloy/cli/__main__.py
tc/alloy/cli/alloy_composition.py
tc/alloy/cli/alloy_list.py
tc/alloy/mcp/__init__.py
tc/alloy/mcp/known_alloy.py
tc/alloy/mcp/resources.py
tc/cli/__init__.py
tc/cli/__main__.py
tc/cli/install.py
tc/cli/options.py
tc/cli/tc_python_check.py
tc/cli/version.py
tc/data/__init__.py
tc/data/mcp/agent.md
tc/database/utils.py
tc/mcp/__init__.py
tc/mcp/__main__.py
tc/mcp/install.py
tc/mcp/types.py
tc/mcp/uninstall.py
tc/mcp/utils.py
tc/mcp/cli/__init__.py
tc/mcp/cli/__main__.py
tc/mcp/cli/install.py
tc/mcp/cli/uninstall.py
tc/property_diagram/__init__.py
tc/property_diagram/calculate_property_diagram.py
tc/property_diagram/compute_quantity.py
tc/property_diagram/defaults.py
tc/property_diagram/resistivity.py
tc/property_diagram/temperatures.py
tc/property_diagram/cli/__init__.py
tc/property_diagram/cli/__main__.py
tc/property_diagram/cli/calculate_property_diagram.py
tc/property_diagram/cli/temperatures.py
tc/property_diagram/mcp/__init__.py
tc/property_diagram/mcp/calculate_property_diagram.py
tc/property_diagram/mcp/compile_material.py
tc/property_diagram/mcp/resistivity.py
tc/property_diagram/mcp/temperatures.py
tc/schema/__init__.py
tc/schema/composition.py
tc/schema/material.py
tc/schema/phase_transformation_temperatures.py
tc/schema/resistivity.py
tc/schema/cli/__init__.py
tc/schema/cli/__main__.py
tc/schema/cli/composition.py
tc/schema/mcp/__init__.py
tc/schema/mcp/composition.py
thermo_calc-0.0.12.dist-info/licenses/LICENSE
thermo_calc-0.0.12.dist-info/METADATA
thermo_calc-0.0.12.dist-info/WHEEL
thermo_calc-0.0.12.dist-info/entry_points.txt
thermo_calc-0.0.12.dist-info/top_level.txt
thermo_calc-0.0.12.dist-info/RECORD
