Metadata-Version: 2.4
Name: thermo-calc
Version: 0.0.12
Summary: Python wrapper for thermo-calc
Author-email: Peter Pak <ppak10@gmail.com>
Project-URL: Homepage, https://github.com/ppak10/thermo-calc
Project-URL: Issues, https://github.com/ppak10/thermo-calc/issues
Requires-Python: >=3.10
License-File: LICENSE
Requires-Dist: mcp>=1.14.0
Requires-Dist: pint>=0.24.4
Requires-Dist: pintdantic>=0.0.0
Requires-Dist: pydantic>=2.11.9
Requires-Dist: rich>=14.1.0
Requires-Dist: typer>=0.17.4
Requires-Dist: workspace-agent>=0.1.9
Dynamic: license-file
